avplib/__init__.py
avplib/__main__.py
avplib/avf.py
avplib/avplib.py
avplib/avplib.pyi
avplib/units.py
avplib-1.5.0.post1.dist-info/METADATA
avplib-1.5.0.post1.dist-info/WHEEL
avplib-1.5.0.post1.dist-info/RECORD
