Metadata-Version: 2.1
Name: avplib
Version: 1.5.0.post1
Summary: AVP - ASCII Video Player. Allows you to play any video as ASCII-art.
Home-page: https://github.com/romanin-rf/avplib
License: MIT
Author: Romanin
Author-email: semina054@gmail.com
Requires-Python: >=3.9,<3.12
Classifier: License :: OSI Approved :: MIT License
Classifier: Programming Language :: Python :: 3
Classifier: Programming Language :: Python :: 3.9
Classifier: Programming Language :: Python :: 3.10
Classifier: Programming Language :: Python :: 3.11
Requires-Dist: click (>=8)
Requires-Dist: ffmpeg (>=1.4)
Requires-Dist: fpstimer (==0.0.1)
Requires-Dist: moviepy (>=1)
Requires-Dist: numpy (>=1.25)
Requires-Dist: opencv-python (>=4.8)
Requires-Dist: pillow (>=10)
Requires-Dist: pygame (>=2.5)
Requires-Dist: rich (>=13.5)
Requires-Dist: soundfile (>=0.12.1)
Project-URL: Repository, https://github.com/romanin-rf/avplib
